auto_depreciation/__init__.py
auto_depreciation/depreciation.py
auto_depreciation-3.1.1.dist-info/LICENSE
auto_depreciation-3.1.1.dist-info/WHEEL
auto_depreciation-3.1.1.dist-info/METADATA
auto_depreciation-3.1.1.dist-info/RECORD
