Metadata-Version: 2.1
Name: auto-depreciation
Version: 3.1.1
Summary: Beancount plugin for fixed assets depreciation
Home-page: https://hktkzyx.github.io/auto-depreciation/
License: GPL-3.0-or-later
Keywords: beancount,plugin
Author: Brooks YUAN
Author-email: hktkzyx@yeah.net
Requires-Python: >=3.9,<4.0
Classifier: License :: OSI Approved :: GNU General Public License v3 or later (GPLv3+)
Classifier: Programming Language :: Python :: 3
Classifier: Programming Language :: Python :: 3.10
Classifier: Programming Language :: Python :: 3.9
Provides-Extra: docs
Provides-Extra: test
Requires-Dist: beancount (>=2.3.5,<3.0.0)
Requires-Dist: mike (>=1.1.2,<2.0.0); extra == "docs"
Requires-Dist: mkdocs (>=1.2.3,<2.0.0); extra == "docs"
Requires-Dist: mkdocs-material (>=8.2.1,<9.0.0); extra == "docs"
Requires-Dist: pytest (>=7.1.2,<8.0.0); extra == "test"
Requires-Dist: pytest-cov (>=3.0.0,<4.0.0); extra == "test"
Requires-Dist: python-dateutil (>=2.8.2,<3.0.0)
Project-URL: Documentation, https://hktkzyx.github.io/auto-depreciation/
Project-URL: Repository, https://github.com/hktkzyx/auto-depreciation
